{
    "name": "basement",
    "longDescription": "You're in the Basement. The cement floor and brick walls bounce every small sound back at you. An eerie howl echoes from outside. There's a bin against one side of the room, along with a pile of cans. The door to the Lower Hall is to the west.",
    "shortDescription": "You're in the Basement. There's a bin against one side of the room, along with a pile of cans. The Lower Hall is to the west.",
    "lockRoom": "True",
    "conditionals": {
        "tincan": {
            "triggerSequence": ["canpile"],
            "loop": "False",
            "0": "All of the cans look empty except one. They have no labels.",
            "1": "All of the cans look empty. They have no labels."
        }
    },
    "exits": {
        "lowerHall": "west"
    },
    "verbInteractions": {
        "Examine": {
            "bin": "It's full of empty tin cans.",
            "canPile": "It's a pile of cans. It smells... unpleasant."
        },
        "Take": {
            "tinCan": "You grab the only unopened can."
        }
    }
}
